{"actions": {"actions": [{"actionDate": "2021-08-03", "committees": [{"name": "Health, Education, Labor, and Pensions Committee", "systemCode": "sshr00", "url": "https://api.congress.gov/v3/committee/senate/sshr00?format=json"}], "sourceSystem": {"name": "Senate"}, "text": "Read twice and referred to the Committee on Health, Education, Labor, and Pensions.", "type": "IntroReferral"}, {"actionCode": "10000", "actionDate": "2021-08-03", "sourceSystem": {"code": 9, "name": "Library of Congress"}, "text": "Introduced in Senate", "type": "IntroReferral"}], "pagination": {"count": 2}, "request": {"billNumber": "2586", "billType": "s", "billUrl": "https://api.congress.gov/v3/bill/117/s/2586?format=json", "congress": "117", "contentType": "application/json", "format": "json"}}, "cosponsors": {"cosponsors": [{"bioguideId": "B001277", "firstName": "Richard", "fullName": "Sen. Blumenthal, Richard [D-CT]", "isOriginalCosponsor": true, "lastName": "Blumenthal", "party": "D", "sponsorshipDate": "2021-08-03", "state": "CT", "url": "https://api.congress.gov/v3/member/B001277?format=json"}, {"bioguideId": "K000367", "firstName": "Amy", "fullName": "Sen. Klobuchar, Amy [D-MN]", "isOriginalCosponsor": true, "lastName": "Klobuchar", "party": "D", "sponsorshipDate": "2021-08-03", "state": "MN", "url": "https://api.congress.gov/v3/member/K000367?format=json"}, {"bioguideId": "V000128", "firstName": "Chris", "fullName": "Sen. Van Hollen, Chris [D-MD]", "isOriginalCosponsor": true, "lastName": "Van Hollen", "party": "D", "sponsorshipDate": "2021-08-03", "state": "MD", "url": "https://api.congress.gov/v3/member/V000128?format=json"}, {"bioguideId": "M000133", "firstName": "Edward", "fullName": "Sen. Markey, Edward J. [D-MA]", "isOriginalCosponsor": true, "lastName": "Markey", "middleName": "J.", "party": "D", "sponsorshipDate": "2021-08-03", "state": "MA", "url": "https://api.congress.gov/v3/member/M000133?format=json"}], "pagination": {"count": 4, "countIncludingWithdrawnCosponsors": 4}, "request": {"billNumber": "2586", "billType": "s", "billUrl": "https://api.congress.gov/v3/bill/117/s/2586?format=json", "congress": "117", "contentType": "application/json", "format": "json"}}, "summaries": {"pagination": {"count": 1}, "request": {"billNumber": "2586", "billType": "s", "billUrl": "https://api.congress.gov/v3/bill/117/s/2586?format=json", "congress": "117", "contentType": "application/json", "format": "json"}, "summaries": [{"actionDate": "2021-08-03", "actionDesc": "Introduced in Senate", "text": " <p><b>Comprehensive TB Elimination Act of </b><b>2021</b></p> <p>This bill reauthorizes for FY2022-FY2027 and revises the tuberculosis (TB) prevention and treatment grant program administered by the Centers for Disease Control and Prevention. The Health Resources and Services Administration may also award grants for TB prevention and treatment efforts to (1) state and local governments; (2) Indian tribes, Native Hawaiian health organizations, and related entities; and (3) community health centers and federally qualified health centers.</p> <p>Additionally, the Government Accountability Office must report on national TB prevention and treatment efforts.</p>", "updateDate": "2021-09-17T18:07:59Z", "versionCode": "00"}]}, "titles": {"pagination": {"count": 3}, "request": {"billNumber": "2586", "billType": "s", "billUrl": "https://api.congress.gov/v3/bill/117/s/2586?format=json", "congress": "117", "contentType": "application/json", "format": "json"}, "titles": [{"title": "Comprehensive TB Elimination Act of 2021", "titleType": "Display Title", "titleTypeCode": 45, "updateDate": "2025-01-03T07:25:32Z"}, {"billTextVersionCode": "IS", "billTextVersionName": "Introduced in Senate", "title": "A bill to amend the Public Health Service Act to enhance the national strategy for combating and eliminating tuberculosis, and for other purposes.", "titleType": "Official Title as Introduced", "titleTypeCode": 6, "updateDate": "2023-01-01T20:17:50Z"}, {"billTextVersionCode": "IS", "billTextVersionName": "Introduced in Senate", "title": "Comprehensive TB Elimination Act of 2021", "titleType": "Short Title(s) as Introduced", "titleTypeCode": 101, "updateDate": "2021-10-23T04:30:17Z"}]}, "meta": {"bill": {"actions": {"count": 2, "url": "https://api.congress.gov/v3/bill/117/s/2586/actions?format=json"}, "committees": {"count": 1, "url": "https://api.congress.gov/v3/bill/117/s/2586/committees?format=json"}, "congress": 117, "cosponsors": {"count": 4, "countIncludingWithdrawnCosponsors": 4, "url": "https://api.congress.gov/v3/bill/117/s/2586/cosponsors?format=json"}, "introducedDate": "2021-08-03", "latestAction": {"actionDate": "2021-08-03", "text": "Read twice and referred to the Committee on Health, Education, Labor, and Pensions."}, "number": "2586", "originChamber": "Senate", "originChamberCode": "S", "policyArea": {"name": "Health"}, "relatedBills": {"count": 1, "url": "https://api.congress.gov/v3/bill/117/s/2586/relatedbills?format=json"}, "sponsors": [{"bioguideId": "B000944", "firstName": "Sherrod", "fullName": "Sen. Brown, Sherrod [D-OH]", "isByRequest": "N", "lastName": "Brown", "party": "D", "state": "OH", "url": "https://api.congress.gov/v3/member/B000944?format=json"}], "subjects": {"count": 1, "url": "https://api.congress.gov/v3/bill/117/s/2586/subjects?format=json"}, "summaries": {"count": 1, "url": "https://api.congress.gov/v3/bill/117/s/2586/summaries?format=json"}, "textVersions": {"count": 1, "url": "https://api.congress.gov/v3/bill/117/s/2586/text?format=json"}, "title": "Comprehensive TB Elimination Act of 2021", "titles": {"count": 3, "url": "https://api.congress.gov/v3/bill/117/s/2586/titles?format=json"}, "type": "S", "updateDate": "2025-01-14T19:02:28Z", "updateDateIncludingText": "2025-01-14T19:02:28Z"}, "request": {"billNumber": "2586", "billType": "s", "congress": "117", "contentType": "application/json", "format": "json"}}}