{"actions": {"actions": [{"actionCode": "H11000", "actionDate": "2022-11-01", "committees": [{"name": "Constitution and Limited Government Subcommittee", "systemCode": "hsju10", "url": "https://api.congress.gov/v3/committee/house/hsju10?format=json"}], "sourceSystem": {"code": 1, "name": "House committee actions"}, "text": "Referred to the Subcommittee on the Constitution, Civil Rights, and Civil Liberties.", "type": "Committee"}, {"actionCode": "H11000", "actionDate": "2022-09-20", "committees": [{"name": "Africa Subcommittee", "systemCode": "hsfa16", "url": "https://api.congress.gov/v3/committee/house/hsfa16?format=json"}], "sourceSystem": {"code": 1, "name": "House committee actions"}, "text": "Referred to the Subcommittee on Africa, Global Health, and Global Human Rights.", "type": "Committee"}, {"actionCode": "H11100", "actionDate": "2022-09-20", "committees": [{"name": "Judiciary Committee", "systemCode": "hsju00", "url": "https://api.congress.gov/v3/committee/house/hsju00?format=json"}], "sourceSystem": {"code": 2, "name": "House floor actions"}, "text": "Referred to the Committee on Foreign Affairs, and in addition to the Committee on the Judiciary, for a period to be subsequently determined by the Speaker, in each case for consideration of such provisions as fall within the jurisdiction of the committee concerned.", "type": "IntroReferral"}, {"actionCode": "H11100", "actionDate": "2022-09-20", "committees": [{"name": "Foreign Affairs Committee", "systemCode": "hsfa00", "url": "https://api.congress.gov/v3/committee/house/hsfa00?format=json"}], "sourceSystem": {"code": 2, "name": "House floor actions"}, "text": "Referred to the Committee on Foreign Affairs, and in addition to the Committee on the Judiciary, for a period to be subsequently determined by the Speaker, in each case for consideration of such provisions as fall within the jurisdiction of the committee concerned.", "type": "IntroReferral"}, {"actionCode": "Intro-H", "actionDate": "2022-09-20", "sourceSystem": {"code": 9, "name": "Library of Congress"}, "text": "Introduced in House", "type": "IntroReferral"}, {"actionCode": "1000", "actionDate": "2022-09-20", "sourceSystem": {"code": 9, "name": "Library of Congress"}, "text": "Introduced in House", "type": "IntroReferral"}], "pagination": {"count": 6}, "request": {"billNumber": "1373", "billType": "hres", "billUrl": "https://api.congress.gov/v3/bill/117/hres/1373?format=json", "congress": "117", "contentType": "application/json", "format": "json"}}, "cosponsors": {"cosponsors": [{"bioguideId": "L000551", "district": 13, "firstName": "BARBARA", "fullName": "Rep. Lee, Barbara [D-CA-13]", "isOriginalCosponsor": true, "lastName": "LEE", "party": "D", "sponsorshipDate": "2022-09-20", "state": "CA", "url": "https://api.congress.gov/v3/member/L000551?format=json"}, {"bioguideId": "R000599", "district": 36, "firstName": "Raul", "fullName": "Rep. Ruiz, Raul [D-CA-36]", "isOriginalCosponsor": true, "lastName": "Ruiz", "party": "D", "sponsorshipDate": "2022-09-20", "state": "CA", "url": "https://api.congress.gov/v3/member/R000599?format=json"}, {"bioguideId": "D000399", "district": 35, "firstName": "LLOYD", "fullName": "Rep. Doggett, Lloyd [D-TX-35]", "isOriginalCosponsor": true, "lastName": "DOGGETT", "party": "D", "sponsorshipDate": "2022-09-20", "state": "TX", "url": "https://api.congress.gov/v3/member/D000399?format=json"}, {"bioguideId": "J000032", "district": 18, "firstName": "SHEILA", "fullName": "Rep. Jackson Lee, Sheila [D-TX-18]", "isOriginalCosponsor": true, "lastName": "JACKSON LEE", "party": "D", "sponsorshipDate": "2022-09-20", "state": "TX", "url": "https://api.congress.gov/v3/member/J000032?format=json"}, {"bioguideId": "J000298", "district": 7, "firstName": "Pramila", "fullName": "Rep. Jayapal, Pramila [D-WA-7]", "isOriginalCosponsor": true, "lastName": "Jayapal", "party": "D", "sponsorshipDate": "2022-09-20", "state": "WA", "url": "https://api.congress.gov/v3/member/J000298?format=json"}, {"bioguideId": "K000389", "district": 17, "firstName": "Ro", "fullName": "Rep. Khanna, Ro [D-CA-17]", "isOriginalCosponsor": true, "lastName": "Khanna", "party": "D", "sponsorshipDate": "2022-09-20", "state": "CA", "url": "https://api.congress.gov/v3/member/K000389?format=json"}, {"bioguideId": "L000586", "district": 5, "firstName": "Al", "fullName": "Rep. Lawson, Al, Jr. [D-FL-5]", "isOriginalCosponsor": true, "lastName": "Lawson", "party": "D", "sponsorshipDate": "2022-09-20", "state": "FL", "url": "https://api.congress.gov/v3/member/L000586?format=json"}, {"bioguideId": "L000592", "district": 9, "firstName": "Andy", "fullName": "Rep. Levin, Andy [D-MI-9]", "isOriginalCosponsor": true, "lastName": "Levin", "party": "D", "sponsorshipDate": "2022-09-20", "state": "MI", "url": "https://api.congress.gov/v3/member/L000592?format=json"}, {"bioguideId": "M000087", "district": 12, "firstName": "CAROLYN", "fullName": "Rep. Maloney, Carolyn B. [D-NY-12]", "isOriginalCosponsor": true, "lastName": "MALONEY", "middleName": "B.", "party": "D", "sponsorshipDate": "2022-09-20", "state": "NY", "url": "https://api.congress.gov/v3/member/M000087?format=json"}, {"bioguideId": "M001143", "district": 4, "firstName": "BETTY", "fullName": "Rep. McCollum, Betty [D-MN-4]", "isOriginalCosponsor": true, "lastName": "MCCOLLUM", "party": "D", "sponsorshipDate": "2022-09-20", "state": "MN", "url": "https://api.congress.gov/v3/member/M001143?format=json"}, {"bioguideId": "M000312", "district": 2, "firstName": "JAMES", "fullName": "Rep. McGovern, James P. [D-MA-2]", "isOriginalCosponsor": true, "lastName": "MCGOVERN", "middleName": "P.", "party": "D", "sponsorshipDate": "2022-09-20", "state": "MA", "url": "https://api.congress.gov/v3/member/M000312?format=json"}, {"bioguideId": "M001196", "district": 6, "firstName": "Seth", "fullName": "Rep. Moulton, Seth [D-MA-6]", "isOriginalCosponsor": true, "lastName": "Moulton", "party": "D", "sponsorshipDate": "2022-09-20", "state": "MA", "url": "https://api.congress.gov/v3/member/M001196?format=json"}, {"bioguideId": "N000147", "district": 0, "firstName": "ELEANOR", "fullName": "Del. Norton, Eleanor Holmes [D-DC-At Large]", "isOriginalCosponsor": true, "lastName": "NORTON", "middleName": "HOLMES", "party": "D", "sponsorshipDate": "2022-09-20", "state": "DC", "url": "https://api.congress.gov/v3/member/N000147?format=json"}, {"bioguideId": "P000618", "district": 45, "firstName": "Katie", "fullName": "Rep. Porter, Katie [D-CA-45]", "isOriginalCosponsor": true, "lastName": "Porter", "party": "D", "sponsorshipDate": "2022-09-20", "state": "CA", "url": "https://api.congress.gov/v3/member/P000618?format=json"}, {"bioguideId": "P000617", "district": 7, "firstName": "Ayanna", "fullName": "Rep. Pressley, Ayanna [D-MA-7]", "isOriginalCosponsor": true, "lastName": "Pressley", "party": "D", "sponsorshipDate": "2022-09-20", "state": "MA", "url": "https://api.congress.gov/v3/member/P000617?format=json"}, {"bioguideId": "S001200", "district": 9, "firstName": "Darren", "fullName": "Rep. Soto, Darren [D-FL-9]", "isOriginalCosponsor": true, "lastName": "Soto", "party": "D", "sponsorshipDate": "2022-09-20", "state": "FL", "url": "https://api.congress.gov/v3/member/S001200?format=json"}, {"bioguideId": "T000481", "district": 13, "firstName": "Rashida", "fullName": "Rep. Tlaib, Rashida [D-MI-13]", "isOriginalCosponsor": true, "lastName": "Tlaib", "party": "D", "sponsorshipDate": "2022-09-20", "state": "MI", "url": "https://api.congress.gov/v3/member/T000481?format=json"}, {"bioguideId": "W000822", "district": 12, "firstName": "Bonnie", "fullName": "Rep. Watson Coleman, Bonnie [D-NJ-12]", "isOriginalCosponsor": true, "lastName": "Watson Coleman", "party": "D", "sponsorshipDate": "2022-09-20", "state": "NJ", "url": "https://api.congress.gov/v3/member/W000822?format=json"}, {"bioguideId": "A000370", "district": 12, "firstName": "Alma", "fullName": "Rep. Adams, Alma S. [D-NC-12]", "isOriginalCosponsor": true, "lastName": "Adams", "middleName": "S.", "party": "D", "sponsorshipDate": "2022-09-20", "state": "NC", "url": "https://api.congress.gov/v3/member/A000370?format=json"}, {"bioguideId": "B000574", "district": 3, "firstName": "EARL", "fullName": "Rep. Blumenauer, Earl [D-OR-3]", "isOriginalCosponsor": true, "lastName": "BLUMENAUER", "party": "D", "sponsorshipDate": "2022-09-20", "state": "OR", "url": "https://api.congress.gov/v3/member/B000574?format=json"}, {"bioguideId": "L000582", "district": 33, "firstName": "Ted", "fullName": "Rep. Lieu, Ted [D-CA-33]", "isOriginalCosponsor": false, "lastName": "Lieu", "party": "D", "sponsorshipDate": "2022-10-25", "state": "CA", "url": "https://api.congress.gov/v3/member/L000582?format=json"}, {"bioguideId": "E000297", "district": 13, "firstName": "Adriano", "fullName": "Rep. Espaillat, Adriano [D-NY-13]", "isOriginalCosponsor": false, "lastName": "Espaillat", "party": "D", "sponsorshipDate": "2022-11-03", "state": "NY", "url": "https://api.congress.gov/v3/member/E000297?format=json"}, {"bioguideId": "R000305", "district": 2, "firstName": "Deborah", "fullName": "Rep. Ross, Deborah K. [D-NC-2]", "isOriginalCosponsor": false, "lastName": "Ross", "middleName": "K.", "party": "D", "sponsorshipDate": "2022-11-03", "state": "NC", "url": "https://api.congress.gov/v3/member/R000305?format=json"}, {"bioguideId": "C001068", "district": 9, "firstName": "Steve", "fullName": "Rep. Cohen, Steve [D-TN-9]", "isOriginalCosponsor": false, "lastName": "Cohen", "party": "D", "sponsorshipDate": "2022-11-15", "state": "TN", "url": "https://api.congress.gov/v3/member/C001068?format=json"}], "pagination": {"count": 24, "countIncludingWithdrawnCosponsors": 24}, "request": {"billNumber": "1373", "billType": "hres", "billUrl": "https://api.congress.gov/v3/bill/117/hres/1373?format=json", "congress": "117", "contentType": "application/json", "format": "json"}}, "summaries": {"pagination": {"count": 1}, "request": {"billNumber": "1373", "billType": "hres", "billUrl": "https://api.congress.gov/v3/bill/117/hres/1373?format=json", "congress": "117", "contentType": "application/json", "format": "json"}, "summaries": [{"actionDate": "2022-09-20", "actionDesc": "Introduced in House", "text": " <p>This resolution expresses the sense that</p> <ul> <li>the federal government should adopt a global health solidarity strategy to end medically avertable deaths and respond to the full burden of disease in poor countries;</li> <li>the federal government should use laws and diplomatic influence to stop ongoing economic harms to the global South; and</li> <li>it is the duty of the federal government to issue reparations, including for slavery and colonialism.</li> </ul>", "updateDate": "2023-08-31T18:53:00Z", "versionCode": "00"}]}, "titles": {"pagination": {"count": 2}, "request": {"billNumber": "1373", "billType": "hres", "billUrl": "https://api.congress.gov/v3/bill/117/hres/1373?format=json", "congress": "117", "contentType": "application/json", "format": "json"}, "titles": [{"title": "Honoring the life of Dr. Paul Farmer by recognizing the duty of the Federal Government to adopt a 21st-century global health solidarity strategy and take actions to address past and ongoing harms that undermine the health and well-being of people around the world.", "titleType": "Display Title", "titleTypeCode": 45, "updateDate": "2022-12-29T12:48:48Z"}, {"billTextVersionCode": "IH", "billTextVersionName": "Introduced in House", "title": "Honoring the life of Dr. Paul Farmer by recognizing the duty of the Federal Government to adopt a 21st-century global health solidarity strategy and take actions to address past and ongoing harms that undermine the health and well-being of people around the world.", "titleType": "Official Title as Introduced", "titleTypeCode": 6, "updateDate": "2022-09-21T07:16:33Z"}]}, "meta": {"bill": {"actions": {"count": 6, "url": "https://api.congress.gov/v3/bill/117/hres/1373/actions?format=json"}, "committees": {"count": 2, "url": "https://api.congress.gov/v3/bill/117/hres/1373/committees?format=json"}, "congress": 117, "cosponsors": {"count": 24, "countIncludingWithdrawnCosponsors": 24, "url": "https://api.congress.gov/v3/bill/117/hres/1373/cosponsors?format=json"}, "introducedDate": "2022-09-20", "latestAction": {"actionDate": "2022-11-01", "text": "Referred to the Subcommittee on the Constitution, Civil Rights, and Civil Liberties."}, "number": "1373", "originChamber": "House", "originChamberCode": "H", "policyArea": {"name": "International Affairs"}, "sponsors": [{"bioguideId": "S001145", "district": 9, "firstName": "JANICE", "fullName": "Rep. Schakowsky, Janice D. [D-IL-9]", "isByRequest": "N", "lastName": "SCHAKOWSKY", "middleName": "D.", "party": "D", "state": "IL", "url": "https://api.congress.gov/v3/member/S001145?format=json"}], "subjects": {"count": 1, "url": "https://api.congress.gov/v3/bill/117/hres/1373/subjects?format=json"}, "summaries": {"count": 1, "url": "https://api.congress.gov/v3/bill/117/hres/1373/summaries?format=json"}, "textVersions": {"count": 1, "url": "https://api.congress.gov/v3/bill/117/hres/1373/text?format=json"}, "title": "Honoring the life of Dr. Paul Farmer by recognizing the duty of the Federal Government to adopt a 21st-century global health solidarity strategy and take actions to address past and ongoing harms that undermine the health and well-being of people around the world.", "titles": {"count": 2, "url": "https://api.congress.gov/v3/bill/117/hres/1373/titles?format=json"}, "type": "HRES", "updateDate": "2025-01-23T13:32:43Z", "updateDateIncludingText": "2025-01-23T13:32:43Z"}, "request": {"billNumber": "1373", "billType": "hres", "congress": "117", "contentType": "application/json", "format": "json"}}, "rolls": {}}